tariff/__init__.py
tariff/__main__.py
tariff/exports.py
tariff_exports-1.1.0.dist-info/licenses/LICENSE
tariff_exports-1.1.0.dist-info/METADATA
tariff_exports-1.1.0.dist-info/WHEEL
tariff_exports-1.1.0.dist-info/top_level.txt
tariff_exports-1.1.0.dist-info/RECORD
