Metadata-Version: 2.4
Name: tariff-exports
Version: 1.1.0
Home-page: https://github.com/e2forks/tariff
Author: Python Economist
Author-email: eterna2@hotmail.com
Keywords: import, tariff, parody, monkey-patch
Classifier: Programming Language :: Python :: 3
Classifier: License :: OSI Approved :: MIT License
Classifier: Operating System :: OS Independent
Classifier: Development Status :: 3 - Alpha
Classifier: Intended Audience :: Developers
Classifier: Topic :: Software Development :: Libraries :: Python Modules
Classifier: Topic :: Utilities
Requires-Python: >=3.6
License-File: LICENSE
Dynamic: author
Dynamic: author-email
Dynamic: home-page
Dynamic: license-file
Dynamic: requires-python
